Metadata-Version: 2.1
Name: cleversession
Version: 0.0.1a1
Summary: A CleverDict subclass to handle selenium webbrowser sessions
Home-page: https://github.com/Pfython/cleversession
Author: Peter Fison
Author-email: peter@southwestlondon.tv
License: MIT License
Download-URL: https://github.com/Pfython/cleversession/archive/0.0.1a1.tar.gz
Keywords: cleversession,Peter Fison,Pfython,
Platform: UNKNOWN
Classifier: Development Status :: 2 - Pre-Alpha
Classifier: Intended Audience :: Developers
Classifier: Operating System :: OS Independent
Classifier: Programming Language :: Python :: 3.6
Classifier: Programming Language :: Python :: 3.7
Classifier: Programming Language :: Python :: 3.8
Classifier: Programming Language :: Python :: 3.9
Classifier: Topic :: Internet
Classifier: Topic :: Internet :: WWW/HTTP :: Browsers
Classifier: Topic :: Internet :: WWW/HTTP :: Indexing/Search
Classifier: Topic :: Internet :: WWW/HTTP :: Session
Classifier: Topic :: Software Development :: Libraries
Classifier: Topic :: Software Development :: Libraries :: Python Modules
Classifier: Topic :: Utilities
Classifier: License :: OSI Approved :: MIT License
